hostlists/__init__.py
hostlists/cli.py
hostlists/decorators.py
hostlists/exceptions.py
hostlists/plugin_base.py
hostlists/plugin_manager.py
hostlists/range.py
hostlists/plugins/__init__.py
hostlists/plugins/dnsip.py
hostlists/plugins/haproxy.py
hostlists/plugins/plugintype.py
hostlists_plugins_default/__init__.py
hostlists_plugins_default/hostlists_plugin_dns.py
hostlists_plugins_default/hostlists_plugin_file.py
hostlists_plugins_default/range.py
hostlists-0.10.669819.dist-info/LICENSE.txt
hostlists-0.10.669819.dist-info/METADATA
hostlists-0.10.669819.dist-info/WHEEL
hostlists-0.10.669819.dist-info/entry_points.txt
hostlists-0.10.669819.dist-info/top_level.txt
hostlists-0.10.669819.dist-info/zip-safe
hostlists-0.10.669819.dist-info/RECORD
