Metadata-Version: 2.1
Name: hostlists
Version: 0.10.669819
Summary: Python module to generate lists of hosts from various sources that is extensible via plugins.
Home-page: https://github.com/yahoo/hostlists
Author: Dwight Hubbard
Author-email: dhubbard@yahoo-inc.com
License: Apache Software License
Project-URL: Documentation, https://yahoo.github.io/hostlists/
Project-URL: Source, https://github.com/yahoo/hostlists
Project-URL: CI Pipeline, https://cd.screwdriver.cd/pipelines/3816
Keywords: hostlist,utility
Platform: UNKNOWN
Classifier: Development Status :: 5 - Production/Stable
Classifier: Environment :: Console
Classifier: Intended Audience :: Developers
Classifier: Intended Audience :: System Administrators
Classifier: License :: OSI Approved :: Apache Software License
Classifier: Natural Language :: English
Classifier: Operating System :: POSIX
Classifier: Operating System :: POSIX :: Linux
Classifier: Operating System :: POSIX :: SunOS/Solaris
Classifier: Operating System :: MacOS :: MacOS X
Classifier: Programming Language :: Python
Classifier: Programming Language :: Python :: 3
Classifier: Programming Language :: Python :: 3.5
Classifier: Programming Language :: Python :: 3.6
Classifier: Programming Language :: Python :: 3.7
Classifier: Programming Language :: Python :: 3.8
Classifier: Programming Language :: Python :: Implementation :: CPython
Classifier: Topic :: System :: Systems Administration
Classifier: Topic :: Utilities
Requires-Python: >="3.5"
Requires-Dist: requests
Requires-Dist: dnspython ; python_version < "3.0"
Requires-Dist: dnspython3 ; python_version >= "3.0"
